{
  "scenes": [
    {
      "id": "8aa8d080-b995-4892-b718-829dd717612c",
      "name": "Main Menu",
      "actors": [
        {
          "id": "f8bfbc69-901f-4ebb-abdf-186f90b64e0a",
          "name": "Sound",
          "components": [
            {
              "name": "AudioSource",
              "config": {
                "src": "audio/menu-music.mp3",
                "volume": 1,
                "looped": true,
                "autoplay": true,
                "group": "music"
              }
            }
          ],
          "children": []
        }
      ]
    },
    {
      "id": "cd85bb20-d3c0-42e1-840b-d5dc5f09daef",
      "name": "Level 1",
      "actors": [
        {
          "id": "8147327a-114d-490e-a8a9-9f2d9a11c888",
          "name": "Background",
          "components": [
            {
              "name": "Sprite",
              "config": {
                "src": "",
                "width": 320,
                "height": 160,
                "slice": 1,
                "rotation": 0,
                "sortCenter": [
                  0,
                  0
                ],
                "flipX": false,
                "flipY": false,
                "sortingLayer": "background",
                "fit": "stretch",
                "blending": "normal",
                "color": "#004e14",
                "opacity": 1
              }
            },
            {
              "name": "Transform",
              "config": {
                "offsetX": 0,
                "offsetY": 0,
                "offsetZ": 0,
                "rotation": 0,
                "scaleX": 1,
                "scaleY": 1
              }
            }
          ],
          "children": []
        },
        {
          "id": "e446dc9c-e7ac-4e73-87fc-8c4410588487",
          "name": "Platform",
          "components": [
            {
              "name": "Transform",
              "config": {
                "offsetX": 0,
                "offsetY": 40,
                "offsetZ": 0,
                "rotation": 0,
                "scaleX": 1,
                "scaleY": 1
              }
            },
            {
              "name": "Sprite",
              "config": {
                "src": "",
                "width": 320,
                "height": 16,
                "slice": 1,
                "rotation": 0,
                "sortCenter": [
                  0,
                  0
                ],
                "flipX": false,
                "flipY": false,
                "sortingLayer": "decorations",
                "fit": "stretch",
                "blending": "normal",
                "color": "#471b00",
                "opacity": 1
              }
            },
            {
              "name": "Collider",
              "config": {
                "type": "box",
                "sizeX": 320,
                "sizeY": 16,
                "centerX": 0,
                "centerY": 0
              }
            },
            {
              "name": "RigidBody",
              "config": {
                "type": "static",
                "mass": 1,
                "useGravity": false,
                "isPermeable": false,
                "ghost": false,
                "drag": 0
              }
            }
          ],
          "children": []
        },
        {
          "id": "5bdc94ae-2af3-48b8-8f20-6637174b6594",
          "name": "Player",
          "components": [
            {
              "name": "Transform",
              "config": {
                "offsetX": 0,
                "offsetY": 0,
                "offsetZ": 0,
                "rotation": 0,
                "scaleX": 1,
                "scaleY": 1
              }
            },
            {
              "name": "Sprite",
              "config": {
                "src": "",
                "width": 16,
                "height": 16,
                "slice": 1,
                "rotation": 0,
                "sortCenter": [
                  0,
                  0
                ],
                "flipX": false,
                "flipY": false,
                "sortingLayer": "units",
                "fit": "stretch",
                "blending": "normal",
                "color": "#212bff",
                "opacity": 1
              }
            },
            {
              "name": "RigidBody",
              "config": {
                "type": "dynamic",
                "mass": 1,
                "useGravity": true,
                "isPermeable": false,
                "ghost": false,
                "drag": 0
              }
            },
            {
              "name": "Collider",
              "config": {
                "type": "box",
                "sizeX": 16,
                "sizeY": 16,
                "centerX": 0,
                "centerY": 0
              }
            },
            {
              "name": "KeyboardControl",
              "config": {
                "inputEventBindings": [
                  {
                    "id": "0a8a3a91-5f51-43fa-b074-38d6fe4c6f64",
                    "key": "KeyA",
                    "pressed": true,
                    "keepEmit": true,
                    "eventType": "Movement",
                    "attrs": [
                      {
                        "id": "be9e797d-c9f7-4864-bc92-e9018f0b2e64",
                        "name": "angle",
                        "type": "number",
                        "value": 180
                      }
                    ]
                  },
                  {
                    "id": "eade1fe5-b361-40d6-bc5d-37730afbf0b3",
                    "key": "KeyD",
                    "pressed": true,
                    "keepEmit": true,
                    "eventType": "Movement",
                    "attrs": [
                      {
                        "id": "6bfc4283-5f89-474a-877b-8aaa756cd6e4",
                        "name": "angle",
                        "type": "string",
                        "value": "0"
                      }
                    ]
                  },
                  {
                    "id": "d8ca42e5-1501-463e-ad2d-e136c231718c",
                    "key": "Space",
                    "pressed": true,
                    "keepEmit": false,
                    "eventType": "MovementJump",
                    "attrs": []
                  }
                ]
              }
            },
            {
              "name": "Movement",
              "config": {
                "speed": 100
              }
            },
            {
              "name": "ViewDirection",
              "config": {
                "x": 0,
                "y": 0
              }
            },
            {
              "name": "Weapon",
              "config": {
                "type": "melee",
                "cooldown": 1000,
                "damage": 1,
                "range": 16
              }
            },
            {
              "name": "MouseControl",
              "config": {
                "inputEventBindings": [
                  {
                    "id": "3410a29c-eb56-4b4c-8f01-b2ac0b8d8192",
                    "event": "mousedown",
                    "eventType": "AttackInput",
                    "attrs": [],
                    "button": 0
                  }
                ]
              }
            },
            {
              "name": "Team",
              "config": {
                "index": 0
              }
            },
            {
              "name": "Behaviors",
              "config": {
                "list": [
                  {
                    "id": "f48ad90f-4c3f-47b4-aa9c-89ea44b96858",
                    "name": "ControlStickBehavior",
                    "options": {}
                  }
                ]
              }
            }
          ],
          "children": []
        },
        {
          "id": "e926e66a-c76c-4cb1-b825-9e8195792288",
          "name": "Enemy",
          "components": [
            {
              "name": "Transform",
              "config": {
                "offsetX": -88,
                "offsetY": 8,
                "offsetZ": 0,
                "rotation": 0,
                "scaleX": 1,
                "scaleY": 1
              }
            },
            {
              "name": "Collider",
              "config": {
                "type": "box",
                "sizeX": 16,
                "sizeY": 16,
                "centerX": 0,
                "centerY": 0
              }
            },
            {
              "name": "Health",
              "config": {
                "points": 1
              }
            },
            {
              "name": "RigidBody",
              "config": {
                "type": "dynamic",
                "mass": 1,
                "useGravity": true,
                "isPermeable": false,
                "ghost": false,
                "drag": 0
              }
            },
            {
              "name": "Sprite",
              "config": {
                "src": "",
                "width": 16,
                "height": 16,
                "slice": 1,
                "rotation": 0,
                "sortCenter": [
                  0,
                  0
                ],
                "flipX": false,
                "flipY": false,
                "sortingLayer": "default",
                "fit": "stretch",
                "blending": "normal",
                "color": "#d30404",
                "opacity": 1
              }
            }
          ],
          "children": [
            {
              "id": "0583d816-4ce7-45da-915b-fae29f14d224",
              "name": "Hit Box",
              "components": [
                {
                  "name": "Transform",
                  "config": {
                    "offsetX": 0,
                    "offsetY": 0,
                    "offsetZ": 0,
                    "rotation": 0,
                    "scaleX": 1,
                    "scaleY": 1
                  }
                },
                {
                  "name": "Collider",
                  "config": {
                    "type": "box",
                    "sizeX": 16,
                    "sizeY": 16,
                    "centerX": 0,
                    "centerY": 0
                  }
                },
                {
                  "name": "HitBox",
                  "config": {}
                }
              ],
              "children": []
            }
          ]
        },
        {
          "id": "99bcc8bb-340a-4e2c-af30-cf993e8aa614",
          "name": "Enemy 2",
          "components": [
            {
              "name": "Transform",
              "config": {
                "offsetX": 88,
                "offsetY": 8,
                "offsetZ": 0,
                "rotation": 0,
                "scaleX": 1,
                "scaleY": 1
              }
            },
            {
              "name": "Collider",
              "config": {
                "type": "box",
                "sizeX": 16,
                "sizeY": 16,
                "centerX": 0,
                "centerY": 0
              }
            },
            {
              "name": "Health",
              "config": {
                "points": 1
              }
            },
            {
              "name": "RigidBody",
              "config": {
                "type": "dynamic",
                "mass": 1,
                "useGravity": true,
                "isPermeable": false,
                "ghost": false,
                "drag": 0
              }
            },
            {
              "name": "Sprite",
              "config": {
                "src": "",
                "width": 16,
                "height": 16,
                "slice": 1,
                "rotation": 0,
                "sortCenter": [
                  0,
                  0
                ],
                "flipX": false,
                "flipY": false,
                "sortingLayer": "default",
                "fit": "stretch",
                "blending": "normal",
                "color": "#d30404",
                "opacity": 1
              }
            }
          ],
          "children": [
            {
              "id": "c0e6da56-daa6-4569-8e66-5f6d2a3bb6c4",
              "name": "Hit Box",
              "components": [
                {
                  "name": "Transform",
                  "config": {
                    "offsetX": 0,
                    "offsetY": 0,
                    "offsetZ": 0,
                    "rotation": 0,
                    "scaleX": 1,
                    "scaleY": 1
                  }
                },
                {
                  "name": "Collider",
                  "config": {
                    "type": "box",
                    "sizeX": 16,
                    "sizeY": 16,
                    "centerX": 0,
                    "centerY": 0
                  }
                },
                {
                  "name": "HitBox",
                  "config": {}
                }
              ],
              "children": []
            }
          ]
        },
        {
          "id": "0a15abde-fc15-4c57-9b1c-9507a474f5cf",
          "name": "Decoration",
          "components": [
            {
              "name": "Sprite",
              "config": {
                "src": "",
                "width": 32,
                "height": 160,
                "slice": 1,
                "rotation": 0,
                "sortCenter": [
                  0,
                  0
                ],
                "flipX": false,
                "flipY": false,
                "sortingLayer": "background-2",
                "fit": "stretch",
                "blending": "normal",
                "color": "#1ce6a5",
                "opacity": 1
              }
            },
            {
              "name": "Transform",
              "config": {
                "offsetX": -112,
                "offsetY": 0,
                "offsetZ": 0,
                "rotation": 0,
                "scaleX": 1,
                "scaleY": 1
              }
            },
            {
              "name": "Parallax",
              "config": {
                "distance": 0.3
              }
            }
          ],
          "children": []
        },
        {
          "id": "e2b29a28-c7a6-4ec4-bc64-746292879581",
          "name": "Decoration 2",
          "components": [
            {
              "name": "Sprite",
              "config": {
                "src": "",
                "width": 32,
                "height": 160,
                "slice": 1,
                "rotation": 0,
                "sortCenter": [
                  0,
                  0
                ],
                "flipX": false,
                "flipY": false,
                "sortingLayer": "background-2",
                "fit": "stretch",
                "blending": "normal",
                "color": "#1ce6a5",
                "opacity": 1
              }
            },
            {
              "name": "Transform",
              "config": {
                "offsetX": 48,
                "offsetY": 0,
                "offsetZ": 0,
                "rotation": 0,
                "scaleX": 1,
                "scaleY": 1
              }
            },
            {
              "name": "Parallax",
              "config": {
                "distance": 0.3
              }
            }
          ],
          "children": []
        },
        {
          "id": "806620c5-1cab-4568-9745-17308c7415dd",
          "name": "Decoration 3",
          "components": [
            {
              "name": "Sprite",
              "config": {
                "src": "",
                "width": 32,
                "height": 32,
                "slice": 1,
                "rotation": 0,
                "sortCenter": [
                  0,
                  0
                ],
                "flipX": false,
                "flipY": false,
                "sortingLayer": "foreground",
                "fit": "stretch",
                "blending": "normal",
                "color": "#c726b5",
                "opacity": 1
              }
            },
            {
              "name": "Transform",
              "config": {
                "offsetX": 96,
                "offsetY": 48,
                "offsetZ": 0,
                "rotation": 0,
                "scaleX": 1,
                "scaleY": 1
              }
            },
            {
              "name": "Parallax",
              "config": {
                "distance": -0.2
              }
            }
          ],
          "children": []
        },
        {
          "id": "a1ab9617-aec6-4766-a0ec-8a80c6eb87df",
          "name": "Decoration 4",
          "components": [
            {
              "name": "Sprite",
              "config": {
                "src": "",
                "width": 32,
                "height": 32,
                "slice": 1,
                "rotation": 0,
                "sortCenter": [
                  0,
                  0
                ],
                "flipX": false,
                "flipY": false,
                "sortingLayer": "foreground",
                "fit": "stretch",
                "blending": "normal",
                "color": "#c726b5",
                "opacity": 1
              }
            },
            {
              "name": "Transform",
              "config": {
                "offsetX": -64,
                "offsetY": 48,
                "offsetZ": 0,
                "rotation": 0,
                "scaleX": 1,
                "scaleY": 1
              }
            },
            {
              "name": "Parallax",
              "config": {
                "distance": -0.2
              }
            }
          ],
          "children": []
        },
        {
          "id": "a067ab21-5153-4130-b1b9-a8c9c4424c3c",
          "name": "Main Camera",
          "components": [
            {
              "name": "Transform",
              "config": {
                "offsetX": 0,
                "offsetY": 0,
                "offsetZ": 0,
                "rotation": 0,
                "scaleX": 1,
                "scaleY": 1
              }
            },
            {
              "name": "Camera",
              "config": {
                "zoom": 1,
                "current": true
              }
            },
            {
              "name": "Behaviors",
              "config": {
                "list": [
                  {
                    "id": "f9e8e789-528c-41d7-b7cd-c11399f1c7a2",
                    "name": "CameraBehavior",
                    "options": {}
                  }
                ]
              }
            },
            {
              "name": "LevelInfo",
              "config": {
                "exampleField": "",
                "index": 0
              }
            }
          ],
          "children": []
        },
        {
          "id": "f245e578-25e7-4c3e-902f-7fa1ffbb8d0b",
          "templateId": "3375b1c1-1495-4e62-9837-4c57890d6a75",
          "name": "Finish",
          "components": [
            {
              "name": "Transform",
              "config": {
                "offsetX": 152,
                "offsetY": 24,
                "offsetZ": 0,
                "rotation": 0,
                "scaleX": 1,
                "scaleY": 1
              }
            }
          ],
          "children": []
        }
      ]
    },
    {
      "id": "abf6f0dd-a66b-418f-8102-5b82b6217383",
      "name": "Level 2",
      "actors": [
        {
          "id": "feba083d-7d75-4a48-931a-519214c6f91c",
          "name": "Background",
          "components": [
            {
              "name": "Sprite",
              "config": {
                "src": "",
                "width": 320,
                "height": 320,
                "slice": 1,
                "rotation": 0,
                "sortCenter": [
                  0,
                  0
                ],
                "flipX": false,
                "flipY": false,
                "sortingLayer": "background",
                "fit": "stretch",
                "blending": "normal",
                "color": "#004e14",
                "opacity": 1
              }
            },
            {
              "name": "Transform",
              "config": {
                "offsetX": 0,
                "offsetY": 0,
                "offsetZ": 0,
                "rotation": 0,
                "scaleX": 1,
                "scaleY": 1
              }
            }
          ],
          "children": []
        },
        {
          "id": "476751fc-7830-4020-8ffd-9f383f0ce591",
          "name": "Player",
          "components": [
            {
              "name": "Transform",
              "config": {
                "offsetX": 0,
                "offsetY": 0,
                "offsetZ": 0,
                "rotation": 0,
                "scaleX": 1,
                "scaleY": 1
              }
            },
            {
              "name": "RigidBody",
              "config": {
                "type": "dynamic",
                "mass": 1,
                "useGravity": false,
                "isPermeable": false,
                "ghost": false,
                "drag": 0
              }
            },
            {
              "name": "Collider",
              "config": {
                "type": "box",
                "sizeX": 16,
                "sizeY": 16,
                "centerX": 0,
                "centerY": 0
              }
            },
            {
              "name": "KeyboardControl",
              "config": {
                "inputEventBindings": [
                  {
                    "id": "0a8a3a91-5f51-43fa-b074-38d6fe4c6f64",
                    "key": "KeyA",
                    "pressed": true,
                    "keepEmit": true,
                    "eventType": "Movement",
                    "attrs": [
                      {
                        "id": "be9e797d-c9f7-4864-bc92-e9018f0b2e64",
                        "name": "angle",
                        "type": "number",
                        "value": 180
                      }
                    ]
                  },
                  {
                    "id": "eade1fe5-b361-40d6-bc5d-37730afbf0b3",
                    "key": "KeyD",
                    "pressed": true,
                    "keepEmit": true,
                    "eventType": "Movement",
                    "attrs": [
                      {
                        "id": "6bfc4283-5f89-474a-877b-8aaa756cd6e4",
                        "name": "angle",
                        "type": "string",
                        "value": "0"
                      }
                    ]
                  },
                  {
                    "id": "d8ca42e5-1501-463e-ad2d-e136c231718c",
                    "key": "KeyW",
                    "pressed": true,
                    "keepEmit": true,
                    "eventType": "Movement",
                    "attrs": [
                      {
                        "id": "16f909ea-2fc1-47e2-b13a-3c69c570d187",
                        "name": "angle",
                        "type": "number",
                        "value": 270
                      }
                    ]
                  },
                  {
                    "id": "a170ea13-a03f-456d-b18c-e4188875e39b",
                    "key": "KeyS",
                    "pressed": true,
                    "keepEmit": true,
                    "eventType": "Movement",
                    "attrs": [
                      {
                        "id": "354ba004-e6c8-4303-9fd1-15cf3e9ccdd8",
                        "name": "angle",
                        "type": "number",
                        "value": 90
                      }
                    ]
                  }
                ]
              }
            },
            {
              "name": "Movement",
              "config": {
                "speed": 100
              }
            },
            {
              "name": "ViewDirection",
              "config": {
                "x": 0,
                "y": 0
              }
            },
            {
              "name": "Weapon",
              "config": {
                "type": "range",
                "cooldown": 500,
                "damage": 1,
                "range": 160,
                "projectileSpeed": 200,
                "projectileRadius": 4,
                "projectileModel": "d01d07c3-ec89-4f61-a2e4-beadcefee92a"
              }
            },
            {
              "name": "MouseControl",
              "config": {
                "inputEventBindings": [
                  {
                    "id": "3410a29c-eb56-4b4c-8f01-b2ac0b8d8192",
                    "event": "mousedown",
                    "eventType": "AttackInput",
                    "attrs": [],
                    "button": 0
                  }
                ]
              }
            },
            {
              "name": "Team",
              "config": {
                "index": 0
              }
            },
            {
              "name": "Sprite",
              "config": {
                "src": "",
                "width": 16,
                "height": 16,
                "slice": 1,
                "rotation": 0,
                "sortCenter": [
                  0,
                  0
                ],
                "flipX": false,
                "flipY": false,
                "sortingLayer": "units",
                "fit": "stretch",
                "blending": "normal",
                "color": "#0005ff",
                "opacity": 1
              }
            },
            {
              "name": "Behaviors",
              "config": {
                "list": [
                  {
                    "id": "731fdf57-bb6b-430c-87fc-6837b148f77c",
                    "name": "ControlStickBehavior",
                    "options": {}
                  }
                ]
              }
            }
          ],
          "children": []
        },
        {
          "id": "70055138-4a42-49b8-a400-5b33918579b8",
          "name": "Enemy",
          "components": [
            {
              "name": "Transform",
              "config": {
                "offsetX": -72,
                "offsetY": 56,
                "offsetZ": 0,
                "rotation": 0,
                "scaleX": 1,
                "scaleY": 1
              }
            },
            {
              "name": "Collider",
              "config": {
                "type": "box",
                "sizeX": 16,
                "sizeY": 16,
                "centerX": 0,
                "centerY": 0
              }
            },
            {
              "name": "Health",
              "config": {
                "points": 1
              }
            },
            {
              "name": "RigidBody",
              "config": {
                "type": "dynamic",
                "mass": 1,
                "useGravity": false,
                "isPermeable": false,
                "ghost": false,
                "drag": 0
              }
            },
            {
              "name": "Sprite",
              "config": {
                "src": "",
                "width": 16,
                "height": 16,
                "slice": 1,
                "rotation": 0,
                "sortCenter": [
                  0,
                  0
                ],
                "flipX": false,
                "flipY": false,
                "sortingLayer": "default",
                "fit": "stretch",
                "blending": "normal",
                "color": "#d30404",
                "opacity": 1
              }
            }
          ],
          "children": [
            {
              "id": "3d500f56-b005-4686-b8b7-f31b114cfb3f",
              "name": "Hit Box",
              "components": [
                {
                  "name": "Transform",
                  "config": {
                    "offsetX": 0,
                    "offsetY": 0,
                    "offsetZ": 0,
                    "rotation": 0,
                    "scaleX": 1,
                    "scaleY": 1
                  }
                },
                {
                  "name": "Collider",
                  "config": {
                    "type": "box",
                    "sizeX": 16,
                    "sizeY": 16,
                    "centerX": 0,
                    "centerY": 0
                  }
                },
                {
                  "name": "HitBox",
                  "config": {}
                }
              ],
              "children": []
            }
          ]
        },
        {
          "id": "f7885966-b39b-4f36-b050-77dee33d444e",
          "name": "Enemy 2",
          "components": [
            {
              "name": "Transform",
              "config": {
                "offsetX": 72,
                "offsetY": -56,
                "offsetZ": 0,
                "rotation": 0,
                "scaleX": 1,
                "scaleY": 1
              }
            },
            {
              "name": "Collider",
              "config": {
                "type": "box",
                "sizeX": 16,
                "sizeY": 16,
                "centerX": 0,
                "centerY": 0
              }
            },
            {
              "name": "Health",
              "config": {
                "points": 1
              }
            },
            {
              "name": "RigidBody",
              "config": {
                "type": "dynamic",
                "mass": 1,
                "useGravity": false,
                "isPermeable": false,
                "ghost": false,
                "drag": 0
              }
            },
            {
              "name": "Sprite",
              "config": {
                "src": "",
                "width": 16,
                "height": 16,
                "slice": 1,
                "rotation": 0,
                "sortCenter": [
                  0,
                  0
                ],
                "flipX": false,
                "flipY": false,
                "sortingLayer": "default",
                "fit": "stretch",
                "blending": "normal",
                "color": "#d30404",
                "opacity": 1
              }
            }
          ],
          "children": [
            {
              "id": "a6bb2eb8-7ba8-4d25-9baa-b70a2b461c9d",
              "name": "Hit Box",
              "components": [
                {
                  "name": "Transform",
                  "config": {
                    "offsetX": 0,
                    "offsetY": 0,
                    "offsetZ": 0,
                    "rotation": 0,
                    "scaleX": 1,
                    "scaleY": 1
                  }
                },
                {
                  "name": "Collider",
                  "config": {
                    "type": "box",
                    "sizeX": 16,
                    "sizeY": 16,
                    "centerX": 0,
                    "centerY": 0
                  }
                },
                {
                  "name": "HitBox",
                  "config": {}
                }
              ],
              "children": []
            }
          ]
        },
        {
          "id": "b3af7323-8d6e-4f0e-8da6-d30ec439dc79",
          "name": "Blocker",
          "components": [
            {
              "name": "Transform",
              "config": {
                "offsetX": -80,
                "offsetY": -64,
                "offsetZ": 0,
                "rotation": 0,
                "scaleX": 1,
                "scaleY": 1
              }
            },
            {
              "name": "Sprite",
              "config": {
                "src": "",
                "width": 32,
                "height": 32,
                "slice": 1,
                "rotation": 0,
                "sortCenter": [
                  0,
                  0
                ],
                "flipX": false,
                "flipY": false,
                "sortingLayer": "decorations",
                "fit": "stretch",
                "blending": "normal",
                "color": "#471b00",
                "opacity": 1
              }
            },
            {
              "name": "Collider",
              "config": {
                "type": "box",
                "sizeX": 32,
                "sizeY": 32,
                "centerX": 0,
                "centerY": 0
              }
            },
            {
              "name": "RigidBody",
              "config": {
                "type": "static",
                "mass": 1,
                "useGravity": false,
                "isPermeable": false,
                "ghost": false,
                "drag": 0
              }
            }
          ],
          "children": []
        },
        {
          "id": "e2849417-da8c-466d-a24b-d1bd00551988",
          "name": "Blocker 2",
          "components": [
            {
              "name": "Transform",
              "config": {
                "offsetX": 48,
                "offsetY": -32,
                "offsetZ": 0,
                "rotation": 0,
                "scaleX": 1,
                "scaleY": 1
              }
            },
            {
              "name": "Sprite",
              "config": {
                "src": "",
                "width": 32,
                "height": 32,
                "slice": 1,
                "rotation": 0,
                "sortCenter": [
                  0,
                  0
                ],
                "flipX": false,
                "flipY": false,
                "sortingLayer": "decorations",
                "fit": "stretch",
                "blending": "normal",
                "color": "#471b00",
                "opacity": 1
              }
            },
            {
              "name": "Collider",
              "config": {
                "type": "box",
                "sizeX": 32,
                "sizeY": 32,
                "centerX": 0,
                "centerY": 0
              }
            },
            {
              "name": "RigidBody",
              "config": {
                "type": "static",
                "mass": 1,
                "useGravity": false,
                "isPermeable": false,
                "ghost": false,
                "drag": 0
              }
            }
          ],
          "children": []
        },
        {
          "id": "a332ef02-b5ea-441c-b0cf-24d7439f33cf",
          "name": "Blocker 3",
          "components": [
            {
              "name": "Transform",
              "config": {
                "offsetX": 16,
                "offsetY": 96,
                "offsetZ": 0,
                "rotation": 0,
                "scaleX": 1,
                "scaleY": 1
              }
            },
            {
              "name": "Sprite",
              "config": {
                "src": "",
                "width": 32,
                "height": 32,
                "slice": 1,
                "rotation": 0,
                "sortCenter": [
                  0,
                  0
                ],
                "flipX": false,
                "flipY": false,
                "sortingLayer": "decorations",
                "fit": "stretch",
                "blending": "normal",
                "color": "#471b00",
                "opacity": 1
              }
            },
            {
              "name": "Collider",
              "config": {
                "type": "box",
                "sizeX": 32,
                "sizeY": 32,
                "centerX": 0,
                "centerY": 0
              }
            },
            {
              "name": "RigidBody",
              "config": {
                "type": "static",
                "mass": 1,
                "useGravity": false,
                "isPermeable": false,
                "ghost": false,
                "drag": 0
              }
            }
          ],
          "children": []
        },
        {
          "id": "f95793b3-dff4-448d-9990-b8ff1f50d872",
          "name": "Main Camera",
          "components": [
            {
              "name": "Transform",
              "config": {
                "offsetX": 0,
                "offsetY": 0,
                "offsetZ": 0,
                "rotation": 0,
                "scaleX": 1,
                "scaleY": 1
              }
            },
            {
              "name": "Camera",
              "config": {
                "zoom": 1,
                "current": true
              }
            },
            {
              "name": "Behaviors",
              "config": {
                "list": [
                  {
                    "id": "f9e8e789-528c-41d7-b7cd-c11399f1c7a2",
                    "name": "CameraBehavior",
                    "options": {}
                  }
                ]
              }
            },
            {
              "name": "LevelInfo",
              "config": {
                "exampleField": "",
                "index": 1
              }
            }
          ],
          "children": []
        },
        {
          "id": "60d47f93-52bf-4429-98df-239d4964bf4e",
          "templateId": "3375b1c1-1495-4e62-9837-4c57890d6a75",
          "name": "Finish",
          "components": [
            {
              "name": "Transform",
              "config": {
                "offsetX": -120,
                "offsetY": 120,
                "offsetZ": 0,
                "rotation": 0,
                "scaleX": 1,
                "scaleY": 1
              }
            }
          ],
          "children": []
        }
      ]
    }
  ],
  "systems": [
    {
      "name": "Saver",
      "options": {}
    },
    {
      "name": "MovementSystem",
      "options": {}
    },
    {
      "name": "PhysicsSystem",
      "options": {
        "gravity": 600
      }
    },
    {
      "name": "CameraSystem",
      "options": {
        "windowNodeId": "root",
        "initialCamera": "0f754dc8-612c-434e-bacd-ba047f23a873",
        "scaleSensitivity": 0
      }
    },
    {
      "name": "MouseInputSystem",
      "options": {
        "useWindow": true
      }
    },
    {
      "name": "KeyboardInputSystem",
      "options": {
        "useWindow": true
      }
    },
    {
      "name": "MouseControlSystem",
      "options": {}
    },
    {
      "name": "KeyboardControlSystem",
      "options": {}
    },
    {
      "name": "CombatSystem",
      "options": {}
    },
    {
      "name": "Reaper",
      "options": {}
    },
    {
      "name": "ParallaxSystem",
      "options": {}
    },
    {
      "name": "BehaviorSystem",
      "options": {}
    },
    {
      "name": "Animator",
      "options": {}
    },
    {
      "name": "Renderer",
      "options": {
        "windowNodeId": "root",
        "backgroundColor": "#000000"
      }
    },
    {
      "name": "UIBridge",
      "options": {}
    },
    {
      "name": "AudioSystem",
      "options": {}
    },
    {
      "name": "GameStatsMeter",
      "options": {
        "frequency": 1000
      }
    }
  ],
  "templates": [
    {
      "id": "92d2fa56-852a-4435-bb4c-d6d3bc15d5f7",
      "name": "Melee Hit",
      "components": [
        {
          "name": "Transform",
          "config": {
            "offsetX": 0,
            "offsetY": 0,
            "offsetZ": 0,
            "rotation": 0,
            "scaleX": 1,
            "scaleY": 1
          }
        },
        {
          "name": "Collider",
          "config": {
            "type": "circle",
            "centerX": 0,
            "centerY": 0,
            "radius": 0
          }
        },
        {
          "name": "Sprite",
          "config": {
            "src": "",
            "width": 16,
            "height": 16,
            "slice": 1,
            "rotation": 0,
            "sortCenter": [
              0,
              0
            ],
            "flipX": false,
            "flipY": false,
            "sortingLayer": "default",
            "fit": "stretch",
            "blending": "normal",
            "color": "#fff",
            "opacity": 1
          }
        }
      ],
      "children": []
    },
    {
      "id": "d01d07c3-ec89-4f61-a2e4-beadcefee92a",
      "name": "Projectile",
      "components": [
        {
          "name": "Transform",
          "config": {
            "offsetX": 0,
            "offsetY": 0,
            "offsetZ": 0,
            "rotation": 0,
            "scaleX": 1,
            "scaleY": 1
          }
        },
        {
          "name": "Collider",
          "config": {
            "type": "circle",
            "centerX": 0,
            "centerY": 0,
            "radius": 0
          }
        },
        {
          "name": "Sprite",
          "config": {
            "src": "",
            "width": 8,
            "height": 8,
            "slice": 1,
            "rotation": 0,
            "sortCenter": [
              0,
              0
            ],
            "flipX": false,
            "flipY": false,
            "sortingLayer": "units",
            "fit": "stretch",
            "blending": "normal",
            "color": "#fff",
            "opacity": 1
          }
        },
        {
          "name": "RigidBody",
          "config": {
            "type": "dynamic",
            "mass": 1,
            "useGravity": false,
            "isPermeable": false,
            "ghost": true,
            "drag": 0
          }
        },
        {
          "name": "Health",
          "config": {
            "points": 1
          }
        }
      ],
      "children": []
    },
    {
      "id": "3375b1c1-1495-4e62-9837-4c57890d6a75",
      "name": "Finish",
      "components": [
        {
          "name": "Transform",
          "config": {
            "offsetX": 0,
            "offsetY": 0,
            "offsetZ": 0,
            "rotation": 0,
            "scaleX": 1,
            "scaleY": 1
          }
        },
        {
          "name": "Shape",
          "config": {
            "type": "rectangle",
            "width": 16,
            "height": 16,
            "strokeWidth": 0,
            "strokeColor": "#fff",
            "strokeAlignment": 0.5,
            "fill": "rgb(255,251,10)",
            "pixelLine": false,
            "sortCenter": [
              0,
              0
            ],
            "sortingLayer": "decorations",
            "blending": "normal",
            "opacity": 1,
            "disabled": false
          }
        },
        {
          "name": "Collider",
          "config": {
            "type": "box",
            "sizeX": 16,
            "sizeY": 16,
            "centerX": 0,
            "centerY": 0
          }
        },
        {
          "name": "Behaviors",
          "config": {
            "list": [
              {
                "id": "eaae0a11-e5e7-41d4-a519-c775a17ebac6",
                "name": "Finish",
                "options": {}
              }
            ]
          }
        }
      ],
      "children": []
    }
  ],
  "globalOptions": [
    {
      "name": "sorting",
      "options": {
        "order": "bottomRight",
        "layers": [
          {
            "id": "388f43fb-4ab3-4973-8dc3-0332ca893ff1",
            "name": "background"
          },
          {
            "id": "688c5812-b0fd-434b-aa24-70ce09be7d11",
            "name": "background-2"
          },
          {
            "id": "2654d67f-bc09-47eb-af47-7b393537a1de",
            "name": "background-3"
          },
          {
            "id": "ddab3636-1184-4c46-ab33-2792b755b5dc",
            "name": "decorations"
          },
          {
            "id": "77f028c4-151b-4094-a16d-3e50e7654a08",
            "name": "decorations-2"
          },
          {
            "id": "3111c97c-6daf-4e32-8bfd-a8420b98f9c9",
            "name": "decorations-3"
          },
          {
            "id": "204715e5-c855-4bc3-b459-06023519ce36",
            "name": "units"
          },
          {
            "id": "cd8c8d30-fe0c-4e48-92b0-926e58600e49",
            "name": "foreground"
          },
          {
            "id": "bb65312e-5873-4b63-99d6-eda457e94b06",
            "name": "default"
          }
        ]
      }
    },
    {
      "name": "audioGroups",
      "options": {
        "groups": [
          {
            "id": "9fcddc8d-250a-4439-b0b3-6f6cb335714e",
            "name": "music",
            "volume": 1
          },
          {
            "id": "0fd17347-48d8-4433-b9fe-f532c8fafd0c",
            "name": "effects",
            "volume": 1
          }
        ]
      }
    },
    {
      "name": "performance",
      "options": {
        "maxFPS": 80,
        "fixedUpdateRate": 60
      }
    }
  ],
  "startSceneId": "8aa8d080-b995-4892-b718-829dd717612c"
}